ui/__init__.py
ui/colors.py
zmunk_ui-1.0.0.dist-info/licenses/LICENSE
zmunk_ui-1.0.0.dist-info/METADATA
zmunk_ui-1.0.0.dist-info/WHEEL
zmunk_ui-1.0.0.dist-info/top_level.txt
zmunk_ui-1.0.0.dist-info/RECORD
