Metadata-Version: 2.4
Name: zmunk-ui
Version: 1.0.0
Summary: Interactive script utilities
Author-email: zmunk <ibrahim.tigrek@gmail.com>
License: MIT License
Project-URL: Homepage, https://github.com/zmunk/ui-python
Keywords: script,ui,interactive
Classifier: License :: OSI Approved :: MIT License
Classifier: Programming Language :: Python
Classifier: Programming Language :: Python :: 3
Requires-Python: >=3.10
License-File: LICENSE
Dynamic: license-file
